{"cameraMode":{"drawMode":0,"name":"Shaded","section":"Shading Mode"},"sceneLighting":true,"audioPlay":false,"sceneViewState":{"showFog":true,"showMaterialUpdate":false,"showSkybox":true,"showFlares":true,"showImageEffects":true,"showParticleSystems":true},"in2DMode":false,"pivot":{"x":-17.85926628112793,"y":2.973318576812744,"z":-19.975479125976564},"rotation":{"x":-0.14716802537441255,"y":0.3220517933368683,"z":-0.05075373873114586,"w":-0.9338362216949463},"size":30.20250701904297,"orthographic":false}